<?xml version="1.0" encoding="UTF-8" ?>
<!DOCTYPE mapper PUBLIC "-//mybatis.org//DTD Mapper 3.0//EN" "http://mybatis.org/dtd/mybatis-3-mapper.dtd" >
<mapper namespace="com.zxf.dao.HousePictureMapper" >
  <resultMap id="BaseResultMap" type="com.zxf.DO.HousePicture" >
    <!--
      WARNING - @mbggenerated
      This element is automatically generated by MyBatis Generator, do not modify.
      This element was generated on Fri Apr 03 15:49:55 CST 2020.
    -->
    <id column="id" property="id" jdbcType="INTEGER" />
    <result column="house_id" property="houseId" jdbcType="INTEGER" />
    <result column="cdn_prefix" property="cdnPrefix" jdbcType="VARCHAR" />
    <result column="width" property="width" jdbcType="INTEGER" />
    <result column="height" property="height" jdbcType="INTEGER" />
    <result column="location" property="location" jdbcType="VARCHAR" />
    <result column="path" property="path" jdbcType="VARCHAR" />
  </resultMap>
  <resultMap id="HousePictureDTO" type="com.zxf.DTO.HousePictureDTO">
    <id column="id" property="id" jdbcType="INTEGER" />
    <result column="house_id" property="houseId" jdbcType="INTEGER" />
    <result column="cdn_prefix" property="cdnPrefix" jdbcType="VARCHAR" />
    <result column="width" property="width" jdbcType="INTEGER" />
    <result column="height" property="height" jdbcType="INTEGER" />
    <result column="path" property="path" jdbcType="VARCHAR" />
  </resultMap>
  <delete id="deleteByPrimaryKey" parameterType="java.lang.Integer" >
    <!--
      WARNING - @mbggenerated
      This element is automatically generated by MyBatis Generator, do not modify.
      This element was generated on Fri Apr 03 15:49:55 CST 2020.
    -->
    delete from house_picture
    where id = #{id,jdbcType=INTEGER}
  </delete>
  <insert id="insert" parameterType="com.zxf.DO.HousePicture" >
    <!--
      WARNING - @mbggenerated
      This element is automatically generated by MyBatis Generator, do not modify.
      This element was generated on Fri Apr 03 15:49:55 CST 2020.
    -->
    insert into house_picture (id, house_id, cdn_prefix, 
      width, height, location, 
      path)
    values (#{id,jdbcType=INTEGER}, #{houseId,jdbcType=INTEGER}, #{cdnPrefix,jdbcType=VARCHAR}, 
      #{width,jdbcType=INTEGER}, #{height,jdbcType=INTEGER}, #{location,jdbcType=VARCHAR}, 
      #{path,jdbcType=VARCHAR})
  </insert>
  <update id="updateByPrimaryKey" parameterType="com.zxf.DO.HousePicture" >
    <!--
      WARNING - @mbggenerated
      This element is automatically generated by MyBatis Generator, do not modify.
      This element was generated on Fri Apr 03 15:49:55 CST 2020.
    -->
    update house_picture
    set house_id = #{houseId,jdbcType=INTEGER},
      cdn_prefix = #{cdnPrefix,jdbcType=VARCHAR},
      width = #{width,jdbcType=INTEGER},
      height = #{height,jdbcType=INTEGER},
      location = #{location,jdbcType=VARCHAR},
      path = #{path,jdbcType=VARCHAR}
    where id = #{id,jdbcType=INTEGER}
  </update>
  <select id="selectByPrimaryKey" resultMap="BaseResultMap" parameterType="java.lang.Integer" >
    <!--
      WARNING - @mbggenerated
      This element is automatically generated by MyBatis Generator, do not modify.
      This element was generated on Fri Apr 03 15:49:55 CST 2020.
    -->
    select id, house_id, cdn_prefix, width, height, location, path
    from house_picture
    where id = #{id,jdbcType=INTEGER}
  </select>
  <select id="selectAll" resultMap="BaseResultMap" >
    <!--
      WARNING - @mbggenerated
      This element is automatically generated by MyBatis Generator, do not modify.
      This element was generated on Fri Apr 03 15:49:55 CST 2020.
    -->
    select id, house_id, cdn_prefix, width, height, location, path
    from house_picture
  </select>

  <insert id="insertBatchHousePictures">
    insert into house_picture
    (
    house_id,
    cdn_prefix,
    width,
    height,
    path
    )
    values
    <foreach collection="list" item="housePictures" separator=",">
      (
           #{housePictures.houseId,jdbcType=INTEGER},
            #{housePictures.cdnPrefix,jdbcType=VARCHAR},
          #{housePictures.width,jdbcType=INTEGER},
           #{housePictures.height,jdbcType=INTEGER},
           #{housePictures.path,jdbcType=VARCHAR}
      )
    </foreach>
  </insert>

  <select id="selectByHouseId" parameterType="java.lang.String" resultMap="BaseResultMap">
    select id, house_id, cdn_prefix, width, height, location, path
    from house_picture
    where house_id = #{id,jdbcType=INTEGER}
  </select>
</mapper>